export_util/__init__.py
export_util/normalize.py
export_util/template.py
export_util/test/test.py
export_util/utility/__init__.py
export_util/utility/cachedprop.py
export_util/utility/schematics.py
export_util/value.py
export_util/writer.py
export_lib-0.4.dist-info/LICENSE
export_lib-0.4.dist-info/WHEEL
export_lib-0.4.dist-info/METADATA
export_lib-0.4.dist-info/RECORD
