Metadata-Version: 2.1
Name: export-lib
Version: 0.4
Summary: 
Author: bmat tvav
Requires-Python: >=3.6.1,<4
Classifier: Programming Language :: Python :: 3
Classifier: Programming Language :: Python :: 3.10
Classifier: Programming Language :: Python :: 3.7
Classifier: Programming Language :: Python :: 3.8
Classifier: Programming Language :: Python :: 3.9
Requires-Dist: openpyxl (>=3.0.9,<4.0.0)
Requires-Dist: reportlab (>=3.6.1,<4.0.0)
Requires-Dist: schematics (>=2.1.1,<3.0.0)
